wgpu/__init__.py
wgpu/_async.py
wgpu/_classes.py
wgpu/_coreutils.py
wgpu/_diagnostics.py
wgpu/_version.py
wgpu/classes.py
wgpu/enums.py
wgpu/flags.py
wgpu/structs.py
wgpu/__pyinstaller/__init__.py
wgpu/__pyinstaller/conftest.py
wgpu/__pyinstaller/hook-wgpu.py
wgpu/__pyinstaller/test_wgpu.py
wgpu/backends/__init__.py
wgpu/backends/auto.py
wgpu/backends/js_webgpu/__init__.py
wgpu/backends/wgpu_native/__init__.py
wgpu/backends/wgpu_native/_api.py
wgpu/backends/wgpu_native/_ffi.py
wgpu/backends/wgpu_native/_helpers.py
wgpu/backends/wgpu_native/_mappings.py
wgpu/backends/wgpu_native/extras.py
wgpu/gui/__init__.py
wgpu/gui/auto.py
wgpu/gui/glfw.py
wgpu/gui/jupyter.py
wgpu/gui/offscreen.py
wgpu/gui/qt.py
wgpu/gui/wx.py
wgpu/resources/__init__.py
wgpu/resources/codegen_report.md
wgpu/resources/webgpu.h
wgpu/resources/webgpu.idl
wgpu/resources/wgpu.h
wgpu/resources/wgpu_native-release.dll
wgpu/utils/__init__.py
wgpu/utils/compute.py
wgpu/utils/device.py
wgpu/utils/glfw_present_info.py
wgpu/utils/imgui/__init__.py
wgpu/utils/imgui/imgui_backend.py
wgpu/utils/imgui/imgui_renderer.py
wgpu/utils/imgui/stats.py
wgpu-0.28.1.dist-info/METADATA
wgpu-0.28.1.dist-info/WHEEL
wgpu-0.28.1.dist-info/entry_points.txt
wgpu-0.28.1.dist-info/licenses/LICENSE
wgpu-0.28.1.dist-info/RECORD
