Metadata-Version: 2.4
Name: wgpu
Version: 0.28.1
Summary: WebGPU for Python
Project-URL: Homepage, https://github.com/pygfx/wgpu-py
Project-URL: Documentation, https://wgpu-py.readthedocs.io
Project-URL: Repository, https://github.com/pygfx/wgpu-py
Author: Almar Klein, Korijn van Golen
License: BSD 2-Clause License
License-File: LICENSE
Keywords: DX12,metal,opengl,vulkan,webgpu,wgpu
Requires-Python: >=3.10
Requires-Dist: cffi>=1.15.0
Requires-Dist: rendercanvas>=2.4
Requires-Dist: rubicon-objc>=0.4.1; sys_platform == 'darwin'
Requires-Dist: sniffio
Provides-Extra: build
Requires-Dist: build; extra == 'build'
Requires-Dist: hatchling; extra == 'build'
Requires-Dist: requests; extra == 'build'
Requires-Dist: twine; extra == 'build'
Provides-Extra: codegen
Requires-Dist: numpy; extra == 'codegen'
Requires-Dist: pytest; extra == 'codegen'
Requires-Dist: ruff; extra == 'codegen'
Provides-Extra: dev
Requires-Dist: anyio; extra == 'dev'
Requires-Dist: build; extra == 'dev'
Requires-Dist: glfw; extra == 'dev'
Requires-Dist: hatchling; extra == 'dev'
Requires-Dist: imageio; extra == 'dev'
Requires-Dist: imgui-bundle; extra == 'dev'
Requires-Dist: numpy; extra == 'dev'
Requires-Dist: pre-commit; extra == 'dev'
Requires-Dist: psutil; extra == 'dev'
Requires-Dist: pypng; extra == 'dev'
Requires-Dist: pytest; extra == 'dev'
Requires-Dist: rendercanvas; extra == 'dev'
Requires-Dist: rendercanvas>=2.4.0; extra == 'dev'
Requires-Dist: requests; extra == 'dev'
Requires-Dist: ruff; extra == 'dev'
Requires-Dist: sphinx-rtd-theme; extra == 'dev'
Requires-Dist: sphinx>7.2; extra == 'dev'
Requires-Dist: trio; extra == 'dev'
Requires-Dist: twine; extra == 'dev'
Provides-Extra: docs
Requires-Dist: sphinx-rtd-theme; extra == 'docs'
Requires-Dist: sphinx>7.2; extra == 'docs'
Provides-Extra: examples
Requires-Dist: glfw; extra == 'examples'
Requires-Dist: imgui-bundle; extra == 'examples'
Requires-Dist: pypng; extra == 'examples'
Requires-Dist: rendercanvas; extra == 'examples'
Provides-Extra: imgui
Requires-Dist: imgui-bundle<2,>=1.92.0; extra == 'imgui'
Provides-Extra: lint
Requires-Dist: pre-commit; extra == 'lint'
Requires-Dist: ruff; extra == 'lint'
Provides-Extra: tests
Requires-Dist: anyio; extra == 'tests'
Requires-Dist: imageio; extra == 'tests'
Requires-Dist: numpy; extra == 'tests'
Requires-Dist: psutil; extra == 'tests'
Requires-Dist: pytest; extra == 'tests'
Requires-Dist: rendercanvas>=2.4.0; extra == 'tests'
Requires-Dist: trio; extra == 'tests'
